{
  "_fv": 18,
  "_type": "recipe",
  "definition": {
    "recipeType": "Crafting",
    "xpReward": 0.0,
    "cookingTime": 200,
    "recipeRetstackSize": 1,
    "group": "",
    "recipeShapeless": false,
    "recipeSlots": [
      {
        "value": "Items.DIAMOND"
      },
      {
        "value": "Items.EMERALD"
      },
      {
        "value": "Items.DIAMOND"
      },
      {
        "value": "Blocks.BEACON"
      },
      {
        "value": "Blocks.ENCHANTING_TABLE"
      },
      {
        "value": "Blocks.BEACON"
      },
      {
        "value": "Items.DIAMOND"
      },
      {
        "value": "Items.EMERALD"
      },
      {
        "value": "Items.DIAMOND"
      }
    ],
    "recipeReturnStack": {
      "value": "CUSTOM:PowerComverter"
    },
    "name": "power_comverter_recipi",
    "namespace": "mod"
  }
}